buzio/__init__.py
buzio/cli.py
buzio/tests.py
buzio-1.1.2.dist-info/DESCRIPTION.rst
buzio-1.1.2.dist-info/METADATA
buzio-1.1.2.dist-info/RECORD
buzio-1.1.2.dist-info/WHEEL
buzio-1.1.2.dist-info/metadata.json
buzio-1.1.2.dist-info/top_level.txt
