Metadata-Version: 2.0
Name: buzio
Version: 1.1.2
Summary: Helpers for command line interaces (CLI) in terminal
Home-page: UNKNOWN
Author: Chris Maillefaud
Author-email: UNKNOWN
License: UNKNOWN
Keywords: terminal input print colorama
Platform: UNKNOWN
Classifier: Development Status :: 4 - Beta
Classifier: Intended Audience :: Developers
Classifier: Topic :: Software Development :: User Interfaces
Classifier: Programming Language :: Python :: 2.7
Classifier: Programming Language :: Python :: 3.5
Classifier: Programming Language :: Python :: 3.6
Requires-Dist: unidecode
Requires-Dist: colorama
